LICENSE
MANIFEST.in
README.md
requirements-serving.txt
requirements.txt
setup.py
LibRecommender_limited.egg-info/PKG-INFO
LibRecommender_limited.egg-info/SOURCES.txt
LibRecommender_limited.egg-info/dependency_links.txt
LibRecommender_limited.egg-info/requires.txt
LibRecommender_limited.egg-info/top_level.txt
libreco/__init__.py
libreco/algorithms/__init__.py
libreco/algorithms/_als.cpp
libreco/algorithms/_als.pyx
libreco/algorithms/_bpr.cpp
libreco/algorithms/_bpr.pyx
libreco/algorithms/als.py
libreco/algorithms/autoint.py
libreco/algorithms/base.py
libreco/algorithms/bpr.py
libreco/algorithms/caser.py
libreco/algorithms/deepfm.py
libreco/algorithms/din.py
libreco/algorithms/fm.py
libreco/algorithms/item_cf.py
libreco/algorithms/knn_embed.py
libreco/algorithms/ncf.py
libreco/algorithms/rnn4rec.py
libreco/algorithms/svd.py
libreco/algorithms/svdpp.py
libreco/algorithms/user_cf.py
libreco/algorithms/wave_net.py
libreco/algorithms/wide_deep.py
libreco/algorithms/youtube_match.py
libreco/algorithms/youtube_ranking.py
libreco/data/__init__.py
libreco/data/data_generator.py
libreco/data/data_info.py
libreco/data/dataset.py
libreco/data/processing.py
libreco/data/sequence.py
libreco/data/split.py
libreco/data/transformed.py
libreco/embedding/__init__.py
libreco/embedding/item2vec.py
libreco/evaluation/__init__.py
libreco/evaluation/computation.py
libreco/evaluation/evaluate.py
libreco/evaluation/metrics.py
libreco/feature/__init__.py
libreco/feature/column.py
libreco/feature/column_mapping.py
libreco/feature/unique_features.py
libreco/utils/__init__.py
libreco/utils/_similarities.cpp
libreco/utils/_similarities.pyx
libreco/utils/exception.py
libreco/utils/initializers.py
libreco/utils/misc.py
libreco/utils/sampling.py
libreco/utils/serialization.py
libreco/utils/similarities.py
libreco/utils/tf_ops.py
serving/__init__.py
serving/flask/__init__.py
serving/flask/colorize.py
serving/flask/save_faiss.py
serving/flask/save_redis.py
serving/flask/knn/knn_deploy.py
serving/flask/knn/knn_request.py
serving/flask/tf/tf_deploy.py
serving/flask/tf/tf_request.py
serving/flask/vector/vector_deploy.py
serving/flask/vector/vector_request.py