Metadata-Version: 2.1
Name: LibRecommender-limited
Version: 0.6.6.2
Summary: A collaborative-filtering and content-based recommender system for both explicit and implicit datasets.
Home-page: https://github.com/massquantity/LibRecommender
Author: massquantity
Author-email: jinxin_madie@163.com
License: MIT
Keywords: Matrix Factorization,Collaborative Filtering,Content-Based,Recommender System,Deep Learning,Data Mining
Platform: UNKNOWN
Classifier: Development Status :: 4 - Beta
Classifier: Intended Audience :: Developers
Classifier: Intended Audience :: Education
Classifier: Intended Audience :: Science/Research
Classifier: License :: OSI Approved :: MIT License
Classifier: Programming Language :: Python :: 3.6
Classifier: Programming Language :: Python :: 3.7
